filmcompress/__init__.py
filmcompress-0.4.4.dist-info/LICENSE
filmcompress-0.4.4.dist-info/METADATA
filmcompress-0.4.4.dist-info/WHEEL
filmcompress-0.4.4.dist-info/entry_points.txt
filmcompress-0.4.4.dist-info/top_level.txt
filmcompress-0.4.4.dist-info/RECORD
