Metadata-Version: 2.1
Name: filmcompress
Version: 0.4.4
Summary: This tool will bulk encode supported videos to HEVC (h.265) or AV1 format in given directory, with optional recursion and optional hardware acceleration.
Home-page: https://github.com/varnav/filmcompress
Author: Evgeny Varnavskiy
Author-email: varnavruz@gmail.com
License: UNKNOWN
Keywords: hevc,video,transcoder,h265,roku
Platform: UNKNOWN
Classifier: Development Status :: 4 - Beta
Classifier: Environment :: MacOS X
Classifier: Environment :: Win32 (MS Windows)
Classifier: Environment :: GPU :: NVIDIA CUDA
Classifier: Intended Audience :: End Users/Desktop
Classifier: License :: OSI Approved :: MIT License
Classifier: Operating System :: OS Independent
Classifier: Topic :: Multimedia :: Video :: Conversion
Classifier: Topic :: Utilities
Classifier: Environment :: Console
Classifier: Programming Language :: Python :: 3.9
Classifier: Programming Language :: Python :: 3 :: Only
Requires-Python: >=3.8
Requires-Dist: click (>=7.1.2)
Requires-Dist: termcolor (>=1.1.0)
Requires-Dist: ffmpeg-python (>=0.2.0)
